qianxun/Emoji.py
qianxun/SDK.py
qianxun/__init__.py
qianxun_wechat_sdk-0.0.3.dist-info/LICENSE.txt
qianxun_wechat_sdk-0.0.3.dist-info/METADATA
qianxun_wechat_sdk-0.0.3.dist-info/WHEEL
qianxun_wechat_sdk-0.0.3.dist-info/top_level.txt
qianxun_wechat_sdk-0.0.3.dist-info/RECORD
