Metadata-Version: 2.1
Name: qianxun-wechat-sdk
Version: 0.0.3
Summary: 千寻微信框架SDK包
Home-page: https://github.com/MaiXiaoMeng/qianxun-wechat-sdk
Author: XiaoMeng Mai
Author-email: beibei857@foxmail.com
Classifier: Programming Language :: Python :: 3
Classifier: License :: OSI Approved :: Apache Software License
Classifier: Operating System :: OS Independent
Requires-Python: >=3.6
License-File: LICENSE.txt
